odoo/addons/l10n_th_bank_payment_export_ktb/README.rst
odoo/addons/l10n_th_bank_payment_export_ktb/__init__.py
odoo/addons/l10n_th_bank_payment_export_ktb/__manifest__.py
odoo/addons/l10n_th_bank_payment_export_ktb/data/bank.export.format.csv
odoo/addons/l10n_th_bank_payment_export_ktb/data/bank.export.format.line.csv
odoo/addons/l10n_th_bank_payment_export_ktb/i18n/l10n_th_bank_payment_export_ktb.pot
odoo/addons/l10n_th_bank_payment_export_ktb/models/__init__.py
odoo/addons/l10n_th_bank_payment_export_ktb/models/bank_export_format.py
odoo/addons/l10n_th_bank_payment_export_ktb/models/bank_payment_export.py
odoo/addons/l10n_th_bank_payment_export_ktb/models/bank_payment_template.py
odoo/addons/l10n_th_bank_payment_export_ktb/models/res_partner.py
odoo/addons/l10n_th_bank_payment_export_ktb/readme/CONTRIBUTORS.rst
odoo/addons/l10n_th_bank_payment_export_ktb/readme/DESCRIPTION.rst
odoo/addons/l10n_th_bank_payment_export_ktb/readme/USAGE.rst
odoo/addons/l10n_th_bank_payment_export_ktb/static/description/icon.png
odoo/addons/l10n_th_bank_payment_export_ktb/static/description/index.html
odoo/addons/l10n_th_bank_payment_export_ktb/templates/__init__.py
odoo/addons/l10n_th_bank_payment_export_ktb/templates/report_bank_payment_export_xlsx.py
odoo/addons/l10n_th_bank_payment_export_ktb/tests/__init__.py
odoo/addons/l10n_th_bank_payment_export_ktb/tests/test_bank_payment_export_ktb.py
odoo/addons/l10n_th_bank_payment_export_ktb/views/bank_payment_export_view.xml
odoo/addons/l10n_th_bank_payment_export_ktb/views/res_partner_views.xml
odoo_addon_l10n_th_bank_payment_export_ktb-15.0.3.0.0.dist-info/METADATA
odoo_addon_l10n_th_bank_payment_export_ktb-15.0.3.0.0.dist-info/WHEEL
odoo_addon_l10n_th_bank_payment_export_ktb-15.0.3.0.0.dist-info/top_level.txt
odoo_addon_l10n_th_bank_payment_export_ktb-15.0.3.0.0.dist-info/RECORD
